faderport.py
faderport-1.0.1.dist-info/METADATA
faderport-1.0.1.dist-info/RECORD
faderport-1.0.1.dist-info/WHEEL
faderport-1.0.1.dist-info/top_level.txt
