Metadata-Version: 2.1
Name: faderport
Version: 1.0.1
Summary: An abstract class to interface with a Presonus FaderPort.
Home-page: https://github.com/jayferg/faderport
Author: jayferg
Author-email: john@ferguson.net.nz
License: MIT
Platform: UNKNOWN
Classifier: Development Status :: 5 - Production/Stable
Classifier: Intended Audience :: Developers
Classifier: Intended Audience :: Science/Research
Classifier: License :: OSI Approved :: MIT License
Classifier: Operating System :: Microsoft :: Windows
Classifier: Programming Language :: Python :: 3.6
Classifier: Topic :: Multimedia :: Sound/Audio :: MIDI
Classifier: Topic :: Scientific/Engineering :: Human Machine Interfaces
Classifier: Topic :: Software Development :: User Interfaces
Classifier: Topic :: System :: Hardware :: Hardware Drivers
Requires-Python: ~=3.6
Requires-Dist: python-rtmidi
Requires-Dist: mido
